{
    "vinuri.2019@iit.ac.lk": {
        "Password": "babullae@123",
        "First Name": "Vinu",
        "Last Name": "Rodrigo"
    },
    "harini.20194@iit.ac.lk": {
        "Password": "Japanees@99",
        "First Name": "Harini",
        "Last Name": "Rodrigo"
    },
    "PassReg.Manager@gmail.com": {
        "Password": "PassaRe@20",
        "First Name": "Passreg",
        "Last Name": "Admin"
    },
    "wer@yahoo.com": {
        "Password": "Don.Daya@123",
        "First Name": "Don",
        "Last Name": "Daya"
    },
    "abc@gmail.com": {
        "Password": "SriJayawa@29",
        "First Name": "Diana",
        "Last Name": "Ellery"
    },
    "viuri.roi21o@outlook.com": {
        "Password": "Australia@22",
        "First Name": "Diana",
        "Last Name": "Shetti"
    }
}